mac2vendors/__init__.py
mac2vendors/cli.py
mac2vendors/mac2vendors.py
mac2vendors/vendors.py
mac2vendors/vendors_json.py
mac2vendors-1.4.0.dist-info/LICENSE.txt
mac2vendors-1.4.0.dist-info/METADATA
mac2vendors-1.4.0.dist-info/WHEEL
mac2vendors-1.4.0.dist-info/entry_points.txt
mac2vendors-1.4.0.dist-info/top_level.txt
mac2vendors-1.4.0.dist-info/RECORD
