Metadata-Version: 2.1
Name: mac2vendors
Version: 1.4.0
Summary: Convert mac addresses to vendor information/ names !
Home-page: https://github.com/4thel00z/swag
Author: ransomware
Author-email: 4thel00z@gmail.com
License: License :: OSI Approved :: GNU Affero General Public License v3 or later (AGPLv3+)
Keywords: mac vendor address converter manuf wireshark arp
Platform: UNKNOWN
Classifier: Development Status :: 4 - Beta
Classifier: Intended Audience :: Developers
Classifier: Topic :: Software Development :: Build Tools
Classifier: License :: OSI Approved :: GNU Affero General Public License v3 or later (AGPLv3+)
Classifier: Programming Language :: Python :: 3
Classifier: Programming Language :: Python :: 3.3
Classifier: Programming Language :: Python :: 3.4
Classifier: Programming Language :: Python :: 3.5
Classifier: Programming Language :: Python :: 3.6
Provides-Extra: dev
Provides-Extra: test
